generatorepiva/__init__.py
generatorepiva/generatorepiva.py
generatorepiva/blob/Codici-statistici-e-denominazioni-al-17_01_2023.csv
generatorepiva-1.0.3.dist-info/METADATA
generatorepiva-1.0.3.dist-info/WHEEL
generatorepiva-1.0.3.dist-info/top_level.txt
generatorepiva-1.0.3.dist-info/RECORD
